geotiepoints/__init__.py
geotiepoints/_modis_interpolator.cp312-win_arm64.pyd
geotiepoints/_modis_utils.cp312-win_arm64.pyd
geotiepoints/_simple_modis_interpolator.cp312-win_arm64.pyd
geotiepoints/basic_interpolator.py
geotiepoints/geointerpolator.py
geotiepoints/interpolator.py
geotiepoints/modisinterpolator.py
geotiepoints/multilinear.py
geotiepoints/multilinear_cython.cp312-win_arm64.pyd
geotiepoints/simple_modis_interpolator.py
geotiepoints/version.py
geotiepoints/viiinterpolator.py
geotiepoints/tests/__init__.py
geotiepoints/tests/test_geointerpolator.py
geotiepoints/tests/test_interpolator.py
geotiepoints/tests/test_modis.py
geotiepoints/tests/test_modisinterpolator.py
geotiepoints/tests/test_multilinear.py
geotiepoints/tests/test_satelliteinterpolator.py
geotiepoints/tests/test_simple_modis_interpolator.py
geotiepoints/tests/test_viiinterpolator.py
geotiepoints/tests/utils.py
python_geotiepoints-1.8.0.dist-info/licenses/LICENSE.txt
python_geotiepoints-1.8.0.dist-info/METADATA
python_geotiepoints-1.8.0.dist-info/WHEEL
python_geotiepoints-1.8.0.dist-info/top_level.txt
python_geotiepoints-1.8.0.dist-info/RECORD
