Metadata-Version: 2.4
Name: python-geotiepoints
Version: 1.8.0
Summary: Interpolation of geographic tiepoints in Python
Home-page: https://github.com/pytroll/python-geotiepoints
Author: Adam Dybbroe, Martin Raspaud
Author-email: martin.raspaud@smhi.se
License: GPL-3.0-or-later
Classifier: Development Status :: 5 - Production/Stable
Classifier: Intended Audience :: Science/Research
Classifier: Operating System :: OS Independent
Classifier: Programming Language :: Python
Classifier: Programming Language :: Cython
Classifier: Topic :: Scientific/Engineering
Classifier: Programming Language :: Python :: Free Threading :: 1 - Unstable
Requires-Python: >=3.11
License-File: LICENSE.txt
Requires-Dist: numpy
Requires-Dist: scipy
Requires-Dist: pandas
Provides-Extra: tests
Requires-Dist: pytest; extra == "tests"
Requires-Dist: pytest-cov; extra == "tests"
Requires-Dist: h5py; extra == "tests"
Requires-Dist: xarray; extra == "tests"
Requires-Dist: dask[array]; extra == "tests"
Requires-Dist: pyproj; extra == "tests"
Requires-Dist: pyresample; extra == "tests"
Dynamic: author
Dynamic: author-email
Dynamic: classifier
Dynamic: description
Dynamic: description-content-type
Dynamic: home-page
Dynamic: license
Dynamic: license-file
Dynamic: provides-extra
Dynamic: requires-dist
Dynamic: requires-python
Dynamic: summary
